cwmungo/.gitignore
cwmungo/__init__.py
cwmungo/crossword_extractor.py
cwmungo-0.2.0.dist-info/LICENSE.txt
cwmungo-0.2.0.dist-info/WHEEL
cwmungo-0.2.0.dist-info/METADATA
cwmungo-0.2.0.dist-info/RECORD
