Metadata-Version: 2.1
Name: cwmungo
Version: 0.2.0
Summary: Extract crossword grids from images
License: MIT
Author: Harry Slatyer
Author-email: harry.slatyer@gmail.com
Requires-Python: >=3.7,<4.0
Classifier: License :: OSI Approved :: MIT License
Classifier: Programming Language :: Python :: 3
Classifier: Programming Language :: Python :: 3.7
Classifier: Programming Language :: Python :: 3.8
Classifier: Programming Language :: Python :: 3.9
Requires-Dist: opencv-python (>=4.5.1,<5.0.0)
